{
    "headerTitle": "Список заказов",
    "lightTheme": "Светлая тема",
    "darkTheme": "Темная тема",
    "searchAreaPlaceholder": "Номер заказа или ФИО",
    "filterButtonText": "Фильтры",
    "filterButtonResetText": "Сбросить фильтры",
    "filterLoaderButtonText": "Загрузка",
    "dropdownItemTexts": [ "Новый", "Расчёт", "Подтверждён", "Отложен", "Выполнен", "Отменен" ],
    "filterRowInputTitles": [ "Дата оформления", "Статус заказа", "Сумма заказа" ],
    "filterRowTextButton": "Применить",
    "filterRowFirstLeftText": "c",
    "filterRowSecondLeftText": "по",
    "filterRowThirdLeftText": "до",
    "filterRowFirstPlaceholder": "dd.mm.dddd",
    "filterRowFirstDefaultValue": "25.10.2022",
    "filterRowSecondPlaceholder": "dd.mm.dddd",
    "filterRowThirdDefaultValue": "5000",
    "filterRowFourthPlaceholder": "₽",
    "filterRowFifthPlaceholder": "Выберите статус",
    "filterRowFifthDefaultValue": "Любой",
    "lightThemText": "Cветлая",
    "darkThemeText": "Темная"
}